LICENSE
MANIFEST.in
README.md
setup.py
hamoco/__init__.py
hamoco/controller.py
hamoco/filter.py
hamoco/hand.py
hamoco/model.py
hamoco.egg-info/PKG-INFO
hamoco.egg-info/SOURCES.txt
hamoco.egg-info/dependency_links.txt
hamoco.egg-info/entry_points.txt
hamoco.egg-info/requires.txt
hamoco.egg-info/top_level.txt
hamoco/cli/__init__.py
hamoco/cli/hamoco_data.py
hamoco/cli/hamoco_run.py
hamoco/cli/hamoco_train.py
hamoco/config/__init__.py
hamoco/config/nt.json
hamoco/config/posix.json
hamoco/core/__init__.py
hamoco/core/_version.py
hamoco/models/__init__.py
hamoco/models/default_model.h5
hamoco/utils/__init__.py
hamoco/utils/utils.py