Metadata-Version: 2.1
Name: hamoco
Version: 1.0.1
Summary: Mouse control via webcam-recorded hand gestures
Home-page: https://github.com/jorisparet/hamoco
Author: Joris Paret
Author-email: joris.paret@gmail.com
Maintainer: Joris Paret
License: GPLv3
Keywords: mouse,controller,webcam,hand,deep learning,neural network
Classifier: License :: OSI Approved :: GNU General Public License v3 (GPLv3)
Classifier: Development Status :: 5 - Production/Stable
Classifier: Topic :: Scientific/Engineering :: Human Machine Interfaces
Classifier: Topic :: Scientific/Engineering :: Image Recognition
Classifier: Programming Language :: Python :: 3
Classifier: Operating System :: POSIX :: Linux
Classifier: Operating System :: Microsoft :: Windows
Classifier: Intended Audience :: End Users/Desktop
Classifier: Natural Language :: English
License-File: LICENSE
